{
  "meta": {
    "title": "Sample SOP: Morning Coffee Routine",
    "owner": ["J. Doe"],
    "version": "1.0.1",
    "goal": "To prepare a perfect cup of coffee to start the day.",
    "purpose": "A standardized procedure for consistent coffee quality."
  },
  "public": {
    "triggers": [
      { "id": "trigger-1", "type": "time_based", "details": "Waking up in the morning" }
    ],
    "nodes": [
      {
        "id": "node-1",
        "label": "Grind Coffee Beans",
        "type": "task",
        "intent": "Grind fresh coffee beans to a medium-fine consistency.",
        "children": ["node-2"]
      },
      {
        "id": "node-2",
        "label": "Boil Water",
        "type": "task",
        "intent": "Heat water to 90-96°C (195-205°F)."
      },
      {
        "id": "node-3",
        "label": "Choose Brew Method",
        "type": "decision",
        "intent": "Decide on the brewing method (e.g., Pour Over, AeroPress).",
        "children": ["node-4", "node-5"]
      },
      {
        "id": "node-4",
        "label": "Prepare Pour Over",
        "type": "task",
        "intent": "Set up the pour over cone, filter, and mug.",
        "children": ["node-6"]
      },
      {
        "id": "node-5",
        "label": "Prepare AeroPress",
        "type": "task",
        "intent": "Set up the AeroPress with filter and coffee grounds.",
        "children": ["node-6"]
      },
      {
        "id": "node-6",
        "label": "Brew Coffee Iteratively",
        "type": "loop",
        "iterator": "Water addition, 50g at a time",
        "exit_condition": "Total water volume reached (e.g., 250g)",
        "intent": "Pour hot water over grounds in stages, allowing for bloom and even extraction."
      },
      {
        "id": "node-7",
        "label": "Enjoy Coffee",
        "type": "end",
        "intent": "Savor the freshly brewed coffee."
      }
    ],
    "variables": {
      "COFFEE_DOSE_G": "15",
      "WATER_TEMP_C": "94",
      "BREW_RATIO": "1:16.67"
    },
    "clarification_requests": [
      {
        "id": "cr-1",
        "question": "What if I only have pre-ground coffee?",
        "status": "answered",
        "answer": "Proceed with pre-ground, but adjust expectations for freshness.",
        "importance": "medium"
      },
      {
        "id": "cr-2",
        "question": "Is a gooseneck kettle mandatory for pour over?",
        "status": "pending",
        "importance": "low"
      }
    ]
  }
} 